<entry name="default">
  <match-list>
    <entry name="Traffic_Log_Forwarding">
      <log-type>traffic</log-type>
      <filter>All Logs</filter>
      <send-to-panorama>yes</send-to-panorama>
    </entry>
    <entry name="Threat_Log_Forwarding">
      <log-type>threat</log-type>
      <filter>All Logs</filter>
      <send-to-panorama>yes</send-to-panorama>
    </entry>
    <entry name="Wildfire_Log_Forwarding">
      <log-type>wildfire</log-type>
      <filter>All Logs</filter>
      <send-to-panorama>yes</send-to-panorama>
    </entry>
    <entry name="URL_Log_Forwarding">
      <log-type>url</log-type>
      <filter>All Logs</filter>
      <send-to-panorama>yes</send-to-panorama>
    </entry>
    <entry name="Data_Log_Forwarding">
      <log-type>data</log-type>
      <filter>All Logs</filter>
      <send-to-panorama>yes</send-to-panorama>
    </entry>
    <entry name="GTP_Log_Forwarding">
      <log-type>gtp</log-type>
      <filter>All Logs</filter>
      <send-to-panorama>yes</send-to-panorama>
    </entry>
    <entry name="Tunnel_Log_Forwarding">
      <log-type>tunnel</log-type>
      <filter>All Logs</filter>
      <send-to-panorama>yes</send-to-panorama>
    </entry>
    <entry name="Auth_Log_Forwarding">
      <log-type>auth</log-type>
      <filter>All Logs</filter>
      <send-to-panorama>yes</send-to-panorama>
    </entry>
  </match-list>
</entry>